sickdt/__init__.py
sickdt/core.py
sickdt-0.1.0.dist-info/LICENSE.txt
sickdt-0.1.0.dist-info/METADATA
sickdt-0.1.0.dist-info/WHEEL
sickdt-0.1.0.dist-info/top_level.txt
sickdt-0.1.0.dist-info/RECORD
