Metadata-Version: 2.1
Name: sickdt
Version: 0.1.0
Summary: Opinionated wrapper over the built-in ``datetime`` module.
Home-page: https://github.com/alexjuda/sickdt
Author: Alexander Juda
Project-URL: Bug Tracker, https://github.com/alexjuda/sickdt/issues
Classifier: Programming Language :: Python :: 3
Classifier: License :: OSI Approved :: Apache Software License
Classifier: Operating System :: OS Independent
Requires-Python: >=3.6
License-File: LICENSE.txt
Provides-Extra: dev
Requires-Dist: pytest ; extra == 'dev'
Requires-Dist: build ; extra == 'dev'
Requires-Dist: twine ; extra == 'dev'
